collective/transmute/__init__.py
collective/transmute/cli.py
collective/transmute/_types/__init__.py
collective/transmute/_types/cli.py
collective/transmute/_types/console.py
collective/transmute/_types/files.py
collective/transmute/_types/pipeline.py
collective/transmute/_types/plone.py
collective/transmute/_types/settings.py
collective/transmute/commands/__init__.py
collective/transmute/commands/info.py
collective/transmute/commands/report.py
collective/transmute/commands/sanity.py
collective/transmute/commands/settings.py
collective/transmute/commands/transmute.py
collective/transmute/layout/__init__.py
collective/transmute/pipeline/__init__.py
collective/transmute/pipeline/pipeline.py
collective/transmute/pipeline/prepare.py
collective/transmute/pipeline/report.py
collective/transmute/reports/__init__.py
collective/transmute/reports/dropped.py
collective/transmute/reports/final_state.py
collective/transmute/reports/paths.py
collective/transmute/settings/__init__.py
collective/transmute/settings/default.toml
collective/transmute/settings/parse.py
collective/transmute/steps/__init__.py
collective/transmute/steps/basic_metadata.py
collective/transmute/steps/blobs.py
collective/transmute/steps/blocks.py
collective/transmute/steps/constraints.py
collective/transmute/steps/creators.py
collective/transmute/steps/data_override.py
collective/transmute/steps/dates.py
collective/transmute/steps/default_page.py
collective/transmute/steps/image.py
collective/transmute/steps/paths.py
collective/transmute/steps/post_querystring.py
collective/transmute/steps/review_state.py
collective/transmute/steps/sanitize.py
collective/transmute/steps/uids.py
collective/transmute/steps/ids/__init__.py
collective/transmute/steps/ids/cleanup.py
collective/transmute/steps/ids/prefixes.py
collective/transmute/steps/portal_type/__init__.py
collective/transmute/steps/portal_type/collection.py
collective/transmute/steps/portal_type/default.py
collective/transmute/utils/__init__.py
collective_transmute-1.0.0a5.dist-info/METADATA
collective_transmute-1.0.0a5.dist-info/WHEEL
collective_transmute-1.0.0a5.dist-info/entry_points.txt
collective_transmute-1.0.0a5.dist-info/RECORD
