Metadata-Version: 2.4
Name: collective.transmute
Version: 1.0.0a5
Summary: Convert data from collective.exportimport to plone.exportimport.
Project-URL: Documentation, https://github.com/collective/collective.transmute#readme
Project-URL: Issues, https://github.com/collective/collective.transmute/issues
Project-URL: Source, https://github.com/collective/collective.transmute
Author-email: Simples Consultoria <contato@simplesconsultoria.com.br>
License-Expression: GPL-2.0
Keywords: Plone,Python,Volto
Classifier: Development Status :: 4 - Beta
Classifier: Environment :: Web Environment
Classifier: Framework :: Plone
Classifier: Framework :: Plone :: 6.1
Classifier: Intended Audience :: Developers
Classifier: Operating System :: OS Independent
Classifier: Programming Language :: Python
Classifier: Programming Language :: Python :: 3.12
Classifier: Programming Language :: Python :: 3.13
Requires-Python: >=3.12
Requires-Dist: aiofiles>=24.1.0
Requires-Dist: collective-html2blocks>=1.0.0a3
Requires-Dist: dynaconf>=3.2.7
Requires-Dist: orjson>=3.10.15
Requires-Dist: tomlkit>=0.13.2
Requires-Dist: typer>=0.15.1
